PPOCRLabel/PPOCRLabel.py
PPOCRLabel/__init__.py
PPOCRLabel/gen_ocr_train_val_test.py
PPOCRLabel/setup.py
PPOCRLabel/libs/__init__.py
PPOCRLabel/libs/autoDialog.py
PPOCRLabel/libs/canvas.py
PPOCRLabel/libs/colorDialog.py
PPOCRLabel/libs/constants.py
PPOCRLabel/libs/create_ml_io.py
PPOCRLabel/libs/editinlist.py
PPOCRLabel/libs/hashableQListWidgetItem.py
PPOCRLabel/libs/keyDialog.py
PPOCRLabel/libs/labelColor.py
PPOCRLabel/libs/labelDialog.py
PPOCRLabel/libs/resources.py
PPOCRLabel/libs/settings.py
PPOCRLabel/libs/shape.py
PPOCRLabel/libs/stringBundle.py
PPOCRLabel/libs/toolBar.py
PPOCRLabel/libs/unique_label_qlist_widget.py
PPOCRLabel/libs/ustr.py
PPOCRLabel/libs/utils.py
PPOCRLabel/libs/zoomWidget.py
StyleText/__init__.py
StyleText/arch/__init__.py
StyleText/arch/base_module.py
StyleText/arch/decoder.py
StyleText/arch/encoder.py
StyleText/arch/spectral_norm.py
StyleText/arch/style_text_rec.py
StyleText/engine/__init__.py
StyleText/engine/corpus_generators.py
StyleText/engine/predictors.py
StyleText/engine/style_samplers.py
StyleText/engine/synthesisers.py
StyleText/engine/text_drawers.py
StyleText/engine/writers.py
StyleText/tools/__init__.py
StyleText/tools/synth_dataset.py
StyleText/tools/synth_image.py
StyleText/utils/__init__.py
StyleText/utils/config.py
StyleText/utils/load_params.py
StyleText/utils/logging.py
StyleText/utils/math_functions.py
StyleText/utils/sys_funcs.py
unstructured_paddleocr/__init__.py
unstructured_paddleocr/paddleocr.py
unstructured_paddleocr/paddle_tools/__init__.py
unstructured_paddleocr/paddle_tools/eval.py
unstructured_paddleocr/paddle_tools/export_center.py
unstructured_paddleocr/paddle_tools/export_model.py
unstructured_paddleocr/paddle_tools/infer_cls.py
unstructured_paddleocr/paddle_tools/infer_det.py
unstructured_paddleocr/paddle_tools/infer_e2e.py
unstructured_paddleocr/paddle_tools/infer_kie.py
unstructured_paddleocr/paddle_tools/infer_kie_token_ser.py
unstructured_paddleocr/paddle_tools/infer_kie_token_ser_re.py
vaaale_paddleocr-2.6.1.3.post2.dist-info/LICENSE
vaaale_paddleocr-2.6.1.3.post2.dist-info/METADATA
vaaale_paddleocr-2.6.1.3.post2.dist-info/WHEEL
vaaale_paddleocr-2.6.1.3.post2.dist-info/top_level.txt
vaaale_paddleocr-2.6.1.3.post2.dist-info/RECORD
