Metadata-Version: 2.1
Name: vaaale_paddleocr
Version: 2.6.1.3.post2
Summary: Awesome OCR toolkits based on PaddlePaddle （8.6M ultra-lightweight pre-trained model, support training and deployment among server, mobile, embeded and IoT devices
Home-page: https://github.com/alevaaga/unstructured.PaddleOCR
Download-URL: https://github.com/alevaaga/unstructured.PaddleOCR.git
License: Apache License 2.0
Keywords: ocr textdetection textrecognition paddleocr crnn east star-net rosetta ocrlite db chineseocr chinesetextdetection chinesetextrecognition
Classifier: Intended Audience :: Developers
Classifier: Operating System :: OS Independent
Classifier: Natural Language :: Chinese (Simplified)
Classifier: Programming Language :: Python :: 3
Classifier: Programming Language :: Python :: 3.2
Classifier: Programming Language :: Python :: 3.3
Classifier: Programming Language :: Python :: 3.4
Classifier: Programming Language :: Python :: 3.5
Classifier: Programming Language :: Python :: 3.6
Classifier: Programming Language :: Python :: 3.7
Classifier: Topic :: Utilities
License-File: LICENSE
Requires-Dist: shapely
Requires-Dist: scikit-image
Requires-Dist: imgaug
Requires-Dist: pyclipper
Requires-Dist: lmdb
Requires-Dist: tqdm
Requires-Dist: numpy
Requires-Dist: visualdl
Requires-Dist: rapidfuzz
Requires-Dist: opencv-python ==4.8.0.76
Requires-Dist: opencv-contrib-python ==4.8.0.76
Requires-Dist: cython
Requires-Dist: lxml
Requires-Dist: premailer
Requires-Dist: openpyxl
Requires-Dist: attrdict
Requires-Dist: Polygon3
Requires-Dist: lanms-neo ==1.0.2
Requires-Dist: pdf2image
